<?xml version="1.0" encoding="UTF-8"?>
<lyrics>
	<lyrictitle>Frustration in My Blood</lyrictitle>
	<romajii>
		<translator>
			<translatorname>Num-Heavymetallic band score</translatorname>
		</translator>
		<lyric>
			<verse>Seiteki shoojo to omoide kozooYoru ni sora no miage mikenekoza wo sagasuSinna mon wa nai sonna mon wa arihashinaiKuruwasu mappiru tainaikairoMANZOKU dekinde urouroMoosootoshi ni hairikonde mayotte shimattaMoosootoshi ni hairikonde mayotte shimattaMomoiro nuttakutta machi aruku ore wa yahari shikijoo ni shitai sareta inu ka?FRUSTRATION IN MY BLOODOre wa katta suikyoobito dattaIma mo kawaranai nan ka shira ga urouroUrouro shitakunatte kuruGuruguru shitakunatte kuruOre wa ore ni niattetaAruku ore wa yahariFRUSTRATION IN MY BLOOD</verse>
		</lyric>
	</romajii>
	<kanji>
		<translator>
			<translatorname>Num-Heavymetallic lyric sheet</translatorname>
		</translator>
		<lyric>
			<verse>性的少女と思い出小僧は夜に空見上げ　三毛猫座を探すしんなもんはない　そんなもんはありはしない狂わす真夜間　体内回路MANZOKUできんでうろうろ妄想都市に入り込んで迷ってしまった妄想都市に入り込んで迷ってしまった桃色ぬったくった街　歩く俺らはやはり色情に支配された犬かFrustration in my blood俺はかった　酔狂人だった今も変わらない　何か知らんがうろうろうろうろしたくなってくるぐるぐるしたくなってくる俺は俺に似合ってた歩く俺はやはりFrustration in my blood</verse>
		</lyric>
	</kanji>
</lyrics>