<?xml version="1.0" encoding="UTF-8"?>
<lyrics>
	<lyrictitle>Sentimenal Girl's Violent Joke</lyrictitle>
	<romajii>
		<translator>
			<translatorname>Greg Bueno</translatorname>
		</translator>
		<lyric>
			<verse>Satsujinteki na JOKE de shinitai ano ko wa takanaiWarai kurui heya n naka wa 32 (san-juu-ni)-INCH no SPEAKER niMAHItta yatsura de ippaiSaratte to ano ko wa itaiWarawasateWaraitobasu nandemo kandemoMukiryoku to kanshoo ittari kitariMayonaka wa nani kutte moo naiWarainagara ano ko wa soo ittaKusa tabako suinagara warainagara KIMEnagaraBooryokuteki na JOKE de shinitai ano ko wa warauJAMAICA tabako wo KImenagaraWarau warau ano ko wa warauWarau kurui satsujinteki ni</verse>
		</lyric>
	</romajii>
	<kanji>
		<translator>
			<translatorname>Urban Guitar Sayonara lyric sheet</translatorname>
		</translator>
		<lyric>
			<verse>殺人的な　ジョークで死にたい　あの娘は泣かない笑い狂う部屋ん中は　３２インチのスピーカーにマヒったやつらでいっぱいさらってとあの娘はいった笑わせて笑い飛ばす　なんでもかんでも無気力と感傷行ったり来たり真夜中は何食ってもうまい笑いながら　あの娘はそう言った草たばこ　すいながら　わらいながら　キメながら暴力的なジョークで死にたい　あの娘は笑うジャマイカたばこをキめながら笑う　笑う　あの娘は笑う笑う狂う　殺人的に</verse>
		</lyric>
	</kanji>
</lyrics>