<?xml version="1.0" encoding="UTF-8"?>
<lyrics>
	<lyrictitle>Freedom</lyrictitle>
	<romajii>
		<translator>
			<translatorname>Fukamidori guitar score</translatorname>
		</translator>
		<lyric>
			<chorus>FREEDOM Very, very STRAWBERRYFREEDOM Very, very CRANBERRYFREEDOM Very, very BLUEBERRY</chorus>
			<verse>Mizu ni utta mori ga mitai yoInochi shirazu no kaze ni naroo yo</verse>
			<chorus>FREEDOM Very, very STRAWBERRYFREEDOM Very, very CRANBERRY</chorus>
			<verse>Furui COAT de tabi ni dekaketaShiranai machi no RESTAURANT de SOUP wo nondeFREEDOM FREEDOM FREEDOMMizu ni utta mori ga mitai yoInochi shirazu no kaze ni naroo yo</verse>
			<chorus>FREEDOM Very, very STRAWBERRYFREEDOM Very, very CRANBERRYFREEDOM Very, very BLUEBERRYFREEDOM Very, very STRAWBERRYFREEDOM Very, very CRANBERRYFREEDOM Very, very BLUEBERRY</chorus>
		</lyric>
	</romajii>
</lyrics>